cacheframe/__init__.py
cacheframe/core.py
cacheframe-0.1.4.dist-info/WHEEL
cacheframe-0.1.4.dist-info/METADATA
cacheframe-0.1.4.dist-info/RECORD
